{
  "name": "/customer/get",
  "nodes": [
    {
      "parameters": {
        "path": "customer/get",
        "responseMode": "responseNode",
        "options": {}
      },
      "id": "0f88b8b1-58c2-4fb9-ac8a-301a0d96c6ee",
      "name": "Webhook",
      "type": "n8n-nodes-base.webhook",
      "typeVersion": 2,
      "position": [
        -1520,
        240
      ],
      "webhookId": "2782bbef-520e-42ff-9a5f-42d491637ce4"
    },
    {
      "parameters": {
        "assignments": {
          "assignments": [
            {
              "id": "field-tenant-id",
              "name": "tenant_id",
              "value": "={{ $json.body.tenant_id }}",
              "type": "string"
            },
            {
              "id": "719a89ea-37b3-4a62-a772-862d51699d0e",
              "name": "id",
              "value": "={{ $json.query.id }}",
              "type": "string"
            }
          ]
        },
        "options": {}
      },
      "id": "2f53eb51-ad33-42d2-b853-4709c484a9d4",
      "name": "Set Fields",
      "type": "n8n-nodes-base.set",
      "typeVersion": 3.4,
      "position": [
        -1344,
        240
      ]
    },
    {
      "parameters": {
        "jsCode": "const tenant_id = ($json.tenant_id || '').trim();\nconst id = ($json.id || '').trim();\n\nconst errors = [];\n\nreturn [{\n  json: {\n    valid: errors.length === 0,\n    errors,\n    tenant_id,\n    id\n  }\n}];"
      },
      "id": "3387ff96-f3be-4f86-8bcc-52b2496d461b",
      "name": "Validate",
      "type": "n8n-nodes-base.code",
      "typeVersion": 2,
      "position": [
        -1152,
        240
      ]
    },
    {
      "parameters": {
        "conditions": {
          "options": {
            "caseSensitive": true,
            "leftValue": "",
            "typeValidation": "strict",
            "version": 1
          },
          "conditions": [
            {
              "id": "cond-valid",
              "leftValue": "={{ $json.valid === true }}",
              "rightValue": true,
              "operator": {
                "type": "boolean",
                "operation": "true"
              }
            }
          ],
          "combinator": "and"
        },
        "options": {}
      },
      "id": "6e2c47fc-02d9-4900-9fd0-6c09ec802a6d",
      "name": "Is Valid?",
      "type": "n8n-nodes-base.if",
      "typeVersion": 2,
      "position": [
        -960,
        240
      ]
    },
    {
      "parameters": {
        "conditions": {
          "options": {
            "caseSensitive": true,
            "leftValue": "",
            "typeValidation": "loose",
            "version": 3
          },
          "conditions": [
            {
              "id": "058660b9-2ee7-4524-baf7-db5fce202546",
              "leftValue": "={{ $json.id }}",
              "rightValue": "",
              "operator": {
                "type": "string",
                "operation": "notEmpty",
                "singleValue": true
              }
            }
          ],
          "combinator": "and"
        },
        "looseTypeValidation": true,
        "options": {}
      },
      "type": "n8n-nodes-base.if",
      "typeVersion": 2.3,
      "position": [
        -720,
        240
      ],
      "id": "915523c6-43b1-4c80-b356-ef8bc1fbac05",
      "name": "Has ID?"
    },
    {
      "parameters": {
        "operation": "executeQuery",
        "query": "select * from public.customer_get_by_id($1, $2);",
        "options": {
          "queryReplacement": "={{ [$('Validate').item.json.tenant_id, $('Validate').item.json.id] }}"
        }
      },
      "type": "n8n-nodes-base.postgres",
      "typeVersion": 2.6,
      "position": [
        -496,
        112
      ],
      "id": "8af2bbbf-8694-4a38-83a4-c863e9b0872c",
      "name": "GET customer by ID",
      "credentials": {
        "postgres": {
          "id": "Enm2PEWvhVMtE5CI",
          "name": "Postgres account"
        }
      }
    },
    {
      "parameters": {
        "operation": "executeQuery",
        "query": "select * from public.customer_get_all($1);",
        "options": {
          "queryReplacement": "={{ [$('Validate').item.json.tenant_id] }}"
        }
      },
      "type": "n8n-nodes-base.postgres",
      "typeVersion": 2.6,
      "position": [
        -496,
        368
      ],
      "id": "a039316c-1f7f-457f-b1a6-ed4770e5a424",
      "name": "Get All Customers",
      "credentials": {
        "postgres": {
          "id": "Enm2PEWvhVMtE5CI",
          "name": "Postgres account"
        }
      }
    },
    {
      "parameters": {
        "conditions": {
          "options": {
            "caseSensitive": true,
            "leftValue": "",
            "typeValidation": "strict",
            "version": 3
          },
          "conditions": [
            {
              "id": "ebc5aaf9-8f47-40c1-8fe9-9ec82330e513",
              "leftValue": "=={{ $input.all().length }}",
              "rightValue": "0",
              "operator": {
                "type": "string",
                "operation": "equals",
                "name": "filter.operator.equals"
              }
            }
          ],
          "combinator": "and"
        },
        "options": {}
      },
      "type": "n8n-nodes-base.if",
      "typeVersion": 2.3,
      "position": [
        -256,
        112
      ],
      "id": "470b5a54-e081-4517-8783-838e2b50b072",
      "name": "Customer found?"
    },
    {
      "parameters": {},
      "type": "n8n-nodes-base.merge",
      "typeVersion": 3.2,
      "position": [
        -32,
        240
      ],
      "id": "7efcf4f4-d440-44d9-b417-711d1c6bff02",
      "name": "Merge"
    },
    {
      "parameters": {
        "assignments": {
          "assignments": [
            {
              "id": "resp-success",
              "name": "success",
              "value": true,
              "type": "boolean"
            },
            {
              "id": "resp-data",
              "name": "data",
              "value": "={{ $input.all().length === 1 ? $input.first().json : $input.all().map(item => item.json) }}",
              "type": "json"
            }
          ]
        },
        "options": {}
      },
      "id": "1896e04d-0fba-4c65-bd75-820a47d8e0cf",
      "name": "Format Response",
      "type": "n8n-nodes-base.set",
      "typeVersion": 3.4,
      "position": [
        176,
        240
      ]
    },
    {
      "parameters": {
        "options": {}
      },
      "id": "83ffb76a-7e2d-4c80-91f1-5c6e7a6310ab",
      "name": "Respond Success",
      "type": "n8n-nodes-base.respondToWebhook",
      "typeVersion": 1.1,
      "position": [
        368,
        240
      ]
    },
    {
      "parameters": {
        "respondWith": "json",
        "responseBody": "={{ { success: false, error: { code: 'VALIDATION_ERROR', message: $json.errors && $json.errors.length ? $json.errors.join(', ') : 'Validation failed' } } }}",
        "options": {
          "responseCode": 400
        }
      },
      "id": "d68de3e0-1e3f-4af7-be2e-b1f95594ed53",
      "name": "Respond Error",
      "type": "n8n-nodes-base.respondToWebhook",
      "typeVersion": 1.1,
      "position": [
        -720,
        432
      ]
    },
    {
      "parameters": {
        "respondWith": "json",
        "responseBody": "={{ { success: false, error: { code: 'NOT_FOUND', message: 'Customer not found' } } }}",
        "options": {
          "responseCode": 404
        }
      },
      "id": "09f9ba0c-eea9-44c5-b223-274de03b7f3a",
      "name": "Respond Error1",
      "type": "n8n-nodes-base.respondToWebhook",
      "typeVersion": 1.1,
      "position": [
        -32,
        -32
      ]
    }
  ],
  "pinData": {},
  "connections": {
    "Webhook": {
      "main": [
        [
          {
            "node": "Set Fields",
            "type": "main",
            "index": 0
          }
        ]
      ]
    },
    "Set Fields": {
      "main": [
        [
          {
            "node": "Validate",
            "type": "main",
            "index": 0
          }
        ]
      ]
    },
    "Validate": {
      "main": [
        [
          {
            "node": "Is Valid?",
            "type": "main",
            "index": 0
          }
        ]
      ]
    },
    "Is Valid?": {
      "main": [
        [
          {
            "node": "Has ID?",
            "type": "main",
            "index": 0
          }
        ],
        [
          {
            "node": "Respond Error",
            "type": "main",
            "index": 0
          }
        ]
      ]
    },
    "Has ID?": {
      "main": [
        [
          {
            "node": "GET customer by ID",
            "type": "main",
            "index": 0
          }
        ],
        [
          {
            "node": "Get All Customers",
            "type": "main",
            "index": 0
          }
        ]
      ]
    },
    "GET customer by ID": {
      "main": [
        [
          {
            "node": "Customer found?",
            "type": "main",
            "index": 0
          }
        ]
      ]
    },
    "Customer found?": {
      "main": [
        [
          {
            "node": "Respond Error1",
            "type": "main",
            "index": 0
          }
        ],
        [
          {
            "node": "Merge",
            "type": "main",
            "index": 0
          }
        ]
      ]
    },
    "Get All Customers": {
      "main": [
        [
          {
            "node": "Merge",
            "type": "main",
            "index": 1
          }
        ]
      ]
    },
    "Merge": {
      "main": [
        [
          {
            "node": "Format Response",
            "type": "main",
            "index": 0
          }
        ]
      ]
    },
    "Format Response": {
      "main": [
        [
          {
            "node": "Respond Success",
            "type": "main",
            "index": 0
          }
        ]
      ]
    }
  },
  "active": true,
  "settings": {
    "executionOrder": "v1",
    "binaryMode": "separate",
    "availableInMCP": false
  },
  "versionId": "a1a82f61-11e0-4a01-8d82-063493d54e59",
  "meta": {
    "instanceId": "db1ba70da077bf2f51c02e462bdc48ed00c6c6a054efdcca5792cc2a2fbe8c64"
  },
  "id": "1hbLaMDhK8xcwUcH",
  "tags": [
    {
      "updatedAt": "2026-03-18T21:55:16.631Z",
      "createdAt": "2026-03-18T21:55:16.631Z",
      "id": "yiaa53DCWGVZFo8L",
      "name": "customer-service"
    }
  ]
}
